testdeneme.py
helloTuran-0.1.2.dist-info/METADATA
helloTuran-0.1.2.dist-info/WHEEL
helloTuran-0.1.2.dist-info/top_level.txt
helloTuran-0.1.2.dist-info/RECORD
