Metadata-Version: 2.1
Name: helloTuran
Version: 0.1.2
Summary: Say helloww
Home-page: UNKNOWN
Author: UNKNOWN
Author-email: UNKNOWN
License: UNKNOWN
Platform: UNKNOWN
